jtag_axi/__init__.py
jtag_axi/jtag_axi_hw.py
jtag_axi/jtag_axi_sim.py
jtag_axi/jtag_base.py
jtag_axi/noxfile.py
jtag_axi/version.py
jtag_axi-0.1.5.dist-info/LICENSE
jtag_axi-0.1.5.dist-info/METADATA
jtag_axi-0.1.5.dist-info/WHEEL
jtag_axi-0.1.5.dist-info/top_level.txt
jtag_axi-0.1.5.dist-info/RECORD
