Metadata-Version: 2.1
Name: jtag-axi
Version: 0.1.5
Summary: JTAG to AXI bridge python I/F
Home-page: https://github.com/aignacio/jtag_axi
Author: aignacio (Anderson Ignacio)
Author-email: <anderson@aignacio.com>
License: MIT
Project-URL: Source Code, https://github.com/aignacio/jtag_axi
Keywords: soc,vip,hdl,verilog,systemverilog,jtag
Classifier: Development Status :: 1 - Planning
Classifier: Intended Audience :: Developers
Classifier: Programming Language :: Python :: 3
Classifier: License :: OSI Approved :: MIT License
Classifier: Operating System :: Unix
Classifier: Operating System :: MacOS :: MacOS X
Classifier: Operating System :: Microsoft :: Windows
Classifier: Topic :: Scientific/Engineering :: Electronic Design Automation (EDA)
Requires-Python: >=3.6
License-File: LICENSE
Requires-Dist: pyftdi
Provides-Extra: test
Requires-Dist: pytest; extra == "test"
Requires-Dist: pyftdi; extra == "test"
